bots/__init__.py
bots/admin.py
bots/apps.py
bots/bots.py
bots/message_types.py
bots/models.py
bots/signals.py
bots/urls.py
bots/utils.py
bots/views.py
bots/management/commands/bot_polling.py
bots/management/commands/bot_polling_from_db.py
bots/management/commands/set_webhooks.py
bots/migrations/0001_initial.py
bots/migrations/0002_auto_20180515_1544.py
bots/migrations/0003_telegrambot_code.py
bots/migrations/0004_telegrambot_settings.py
bots/migrations/0005_auto_20180701_1514.py
bots/migrations/0006_telegrambot_owners.py
bots/migrations/__init__.py
telebakacore-0.1.18.dist-info/METADATA
telebakacore-0.1.18.dist-info/WHEEL
telebakacore-0.1.18.dist-info/top_level.txt
telebakacore-0.1.18.dist-info/RECORD
