Metadata-Version: 2.1
Name: telebakacore
Version: 0.1.18
Summary: UNKNOWN
Home-page: UNKNOWN
Author: bakatrouble
Author-email: bakatrouble@gmail.com
License: UNKNOWN
Platform: UNKNOWN
Requires-Dist: django
Requires-Dist: python-telegram-bot
Requires-Dist: lazy-object-proxy
Requires-Dist: uuid
Requires-Dist: django-jsonview
Requires-Dist: raven
Requires-Dist: jsonfield
